upgrade_knausj/__init__.py
upgrade_knausj/git.py
upgrade_knausj/handle_challenging_commit.py
upgrade_knausj/main.py
upgrade_knausj/setup.py
upgrade_knausj/util.py
upgrade_knausj-0.3.15.dist-info/entry_points.txt
upgrade_knausj-0.3.15.dist-info/WHEEL
upgrade_knausj-0.3.15.dist-info/METADATA
upgrade_knausj-0.3.15.dist-info/RECORD
