Metadata-Version: 2.1
Name: upgrade-knausj
Version: 0.3.15
Summary: 
Author: Pokey Rule
Author-email: 755842+pokey@users.noreply.github.com
Requires-Python: >=3.10,<4.0
Classifier: Programming Language :: Python :: 3
Classifier: Programming Language :: Python :: 3.10
Classifier: Programming Language :: Python :: 3.11
Requires-Dist: gitpython (>=3.1.29,<4.0.0)
Requires-Dist: pre-commit (>=2.20.0,<3.0.0)
Requires-Dist: pyyaml (>=6.0,<7.0)
Requires-Dist: rich (>=12.6.0,<13.0.0)
Requires-Dist: typer[all] (>=0.7.0,<0.8.0)
